{"cameraMode":{"drawMode":0,"name":"Shaded","section":"Shading Mode"},"sceneLighting":true,"audioPlay":false,"sceneViewState":{"showFog":true,"showMaterialUpdate":false,"showSkybox":true,"showFlares":true,"showImageEffects":true,"showParticleSystems":true},"in2DMode":false,"pivot":{"x":-0.4124249517917633,"y":-0.5659127235412598,"z":-0.24659445881843568},"rotation":{"x":0.12656471133232118,"y":-0.8717980980873108,"z":0.30477169156074526,"w":0.3620380759239197},"size":4.807394981384277,"orthographic":false}